mibale/init.py
mibale/android/bridge.py
mibale/android/renderer/android_renderer.py
mibale/android/renderer/view_factory.py
mibale/builder/android_builder.py
mibale/builder/app_builder.py
mibale/builder/init.py
mibale/builder/ios_builder.py
mibale/cli/mibale_cli.py
mibale/compiler/mb_compiler.py
mibale/components/ar_vr.py
mibale/components/camera.py
mibale/components/connectivity.py
mibale/components/device.py
mibale/components/init.py
mibale/components/media.py
mibale/components/microphone.py
mibale/components/native_components.py
mibale/components/sensors.py
mibale/core/application.py
mibale/core/component.py
mibale/core/reactive.py
mibale/dev/dev_server.py
mibale/dev/file_watcher.py
mibale/dev/hot_reloader.py
mibale/dev/init.py
mibale/ios/bridge.py
mibale/ios/init.py
mibale/ios/renderer/init.py
mibale/ios/renderer/ios_renderer.py
mibale/ios/renderer/view_factory.py
mibale/render/layout_manager.py
mibale/render/native_renderer.py
mibale/render/render_engine.py
mibale/render/style_engine.py
mibale/render/virtual_dom.py
mibale/router/router.py
mibale/services/http_client.py
mibale/stores/store.py
mibale/templates/default/init.py
mibale/templates/default/mibale.config.py
mibale/templates/default/requirements.txt
mibale/templates/default/src/main.py
mibale/templates/default/src/components/HelloWorld.mb
mibale/templates/default/src/router/routes.py
mibale/templates/default/src/services/api.py
mibale/templates/default/src/stores/user_store.py
mibale/templates/default/src/views/AboutView.mb
mibale/templates/default/src/views/HomeView.mb
mibale/templates/default/static/images/README.md
mibale-1.1.2.dist-info/METADATA
mibale-1.1.2.dist-info/WHEEL
mibale-1.1.2.dist-info/entry_points.txt
mibale-1.1.2.dist-info/top_level.txt
mibale-1.1.2.dist-info/RECORD
